{
	"class" : {
		"newWith:" : "AS 5/24/2018 10:13" },
	"instance" : {
		"addColumnAfter" : "AS 6/12/2018 16:57",
		"addColumnBefore" : "lh 6/9/2018 13:30",
		"addColumnWithIndex:" : "LH 6/12/2018 20:36",
		"addDependencies" : "AS 5/24/2018 10:39",
		"addFunctionWindow" : "AS 5/22/2018 23:31",
		"addRowAfter" : "lh 6/9/2018 14:29",
		"addRowBefore" : "lh 6/9/2018 17:08",
		"addRowWithIndex:" : "LH 6/12/2018 20:37",
		"bottom" : "AS 5/24/2018 10:06",
		"calculateSizeForWidth:" : "AS 5/25/2018 09:38",
		"cellAtRowIndex:colIndex:" : "lh 5/30/2018 18:19",
		"changeHeight:at:" : "LB 5/7/2018 15:14",
		"changeWidth" : "AS 5/18/2018 14:55",
		"changeWidth:at:" : "LB 5/7/2018 15:15",
		"columns" : "AS 5/3/2018 17:02",
		"editCell:event:" : "AS 5/20/2018 23:16",
		"editor" : "AS 5/16/2018 17:03",
		"editor:" : "AS 5/16/2018 17:03",
		"functionWindow" : "PH 5/21/2018 20:52",
		"functionWindow:" : "PH 5/21/2018 20:52",
		"getCellContentForPointCollection:" : "lh 5/30/2018 20:04",
		"getCellsFrom:to:" : "AS 5/30/2018 12:21",
		"grabbed" : "LH 5/6/2018 13:32",
		"grabbed:" : "LH 5/6/2018 13:32",
		"gridBounds" : "AS 5/18/2018 19:13",
		"gridSize" : "AS 5/25/2018 09:38",
		"initialize" : "lh 6/9/2018 16:01",
		"markAllLabel" : "AS 5/24/2018 10:04",
		"markAllLabel:" : "AS 5/24/2018 10:04",
		"markedColumns" : "AS 5/17/2018 14:06",
		"markedColumns:" : "AS 5/20/2018 22:35",
		"mouseDown:" : "LH 5/6/2018 13:32",
		"mouseStillDown:" : "AS 5/18/2018 16:41",
		"mouseUp:" : "AS 5/18/2018 16:42",
		"removeColumn" : "lh 6/9/2018 13:24",
		"removeColumnWithIndex:" : "LH 6/12/2018 20:39",
		"removeRow" : "lh 6/9/2018 13:29",
		"removeRowWithIndex:" : "LH 6/12/2018 20:39",
		"right" : "AS 5/24/2018 10:05",
		"rows" : "AS 5/3/2018 17:04",
		"selectAll" : "AS 5/24/2018 10:32",
		"selection" : "AS 5/30/2018 12:24",
		"standardGridSize" : "AS 5/18/2018 18:04",
		"standardPosition" : "AS 5/3/2018 18:34",
		"startDragAtCell:" : "AS 5/19/2018 15:33",
		"startDragAtLabel:" : "AS 5/30/2018 09:54",
		"stopDragAtCell:" : "AS 5/18/2018 16:55",
		"updateDragPosition:" : "AS 5/30/2018 09:32",
		"updateDragPositionLabel:" : "AS 6/12/2018 18:05" } }
